{"@context":"https://iiif.io/api/presentation/3/context.json","id":"https://yian2024.github.io/LLP-Exhibition/api/facet/genre/hair-material.json","type":"Collection","label":{"none":["hair (material)"]},"items":[{"id":"https://api.dc.library.northwestern.edu/api/v2/works/1e3c6799-2461-45ff-9eb7-7dff505bf1af?as=iiif","type":"Manifest","label":{"none":["Lock of hair"]},"thumbnail":[{"id":"https://api.dc.library.northwestern.edu/api/v2/works/1e3c6799-2461-45ff-9eb7-7dff505bf1af/thumbnail","type":"Image","format":"image/jpeg","height":300,"width":300}],"homepage":[{"id":"https://yian2024.github.io/LLP-Exhibition/works/lock-of-hair","type":"Text","label":{"none":["Lock of hair"]}}]}],"partOf":[{"id":"https://yian2024.github.io/LLP-Exhibition/api/facet/genre.json","type":"Collection"}],"summary":{"none":["Genre"]},"homepage":[{"id":"https://yian2024.github.io/LLP-Exhibition/search?genre=hair-material","type":"Text","label":{"none":["hair (material)"]}}]}