{"@context":"https://iiif.io/api/presentation/3/context.json","id":"https://canopy-iiif.github.io/canopy-iiif/api/facet/date/august-19-1953.json","type":"Collection","label":{"none":["August 19, 1953"]},"items":[{"id":"https://api.dc.library.northwestern.edu/api/v2/works/4d369c97-a64b-49ab-ba4e-0c14883fc641?as=iiif","type":"Manifest","label":{"none":["Second Section of Safari Film Slated Sept. 14."]},"thumbnail":[{"id":"https://api.dc.library.northwestern.edu/api/v2/works/4d369c97-a64b-49ab-ba4e-0c14883fc641/thumbnail","type":"Image","format":"image/jpeg","height":300,"width":300}],"homepage":[{"id":"https://canopy-iiif.github.io/canopy-iiif/works/second-section-of-safari-film-slated-sept-14","type":"Text","label":{"none":["Second Section of Safari Film Slated Sept. 14."]}}]}],"partOf":[{"id":"https://canopy-iiif.github.io/canopy-iiif/api/facet/date.json","type":"Collection"}],"summary":{"none":["Date"]},"homepage":[{"id":"https://canopy-iiif.github.io/canopy-iiif/search?date=august-19-1953","type":"Text","label":{"none":["August 19, 1953"]}}]}